roulettes/__init__.py
roulettes-1.0.0.dist-info/WHEEL
roulettes-1.0.0.dist-info/METADATA
roulettes-1.0.0.dist-info/RECORD
