Metadata-Version: 2.1
Name: roulettes
Version: 1.0.0
Summary: Add roulettes to your something.
Author: Ivulka
Requires-Python: >=3.10,<4.0
Classifier: Programming Language :: Python :: 3
Classifier: Programming Language :: Python :: 3.10
